{
  "menu": [
    {
      "img": "img/tabs/vegy.jpg",
      "altimg": "vegy",
      "title": "Меню 'Фитнес'",
      "descr": "Меню 'Фитнес' - это новый подход к приготовлению блюд: больше свежих овощей и фруктов. Продукт активных и здоровых людей. Это абсолютно новый продукт с оптимальной ценой и высоким качеством!",
      "price": 9
    },
    {
      "img": "img/tabs/post.jpg",
      "altimg": "post",
      "title": "Меню 'Постное'",
      "descr": "Меню 'Постное' - это тщательный подбор ингредиентов: полное отсутствие продуктов животного происхождения, молоко из миндаля, овса, кокоса или гречки, правильное количество белков за счет тофу и импортных вегетарианских стейков.",
      "price": 14
    },
    {
      "img": "img/tabs/elite.jpg",
      "altimg": "elite",
      "title": "Меню 'Премиум'",
      "descr": "В меню 'Премиум' мы используем не только красивый дизайн упаковки, но и качественное исполнение блюд. Красная рыба, морепродукты, фрукты - ресторанное меню без похода в ресторан!",
      "price": 21
    }
  ],
  "requests": [
    {
      "name": "achhamana",
      "phone": "+38 (099) 917-19-25",
      "id": 1
    },
    {
      "name": "achhamana",
      "phone": "+38 (099) 917-19-25",
      "id": 2
    },
    {
      "name": "achhamana",
      "phone": "+38 (099) 917-19-25",
      "id": 3
    },
    {
      "name": "Nikita",
      "phone": "0736289394",
      "id": 4
    },
    {
      "name": "achhamana",
      "phone": "+38 (099) 917-19-25",
      "id": 5
    },
    {
      "name": "Nikita",
      "phone": "123",
      "id": 6
    },
    {
      "name": "achhamana",
      "phone": "+38 (099) 917-19-25",
      "id": 7
    },
    {
      "name": "Никита",
      "phone": "+38 (099) 917-19-25",
      "id": 8
    },
    {
      "name": "Никита",
      "phone": "+38 (099) 917-19-25",
      "id": 9
    },
    {
      "name": "achhamana",
      "phone": "+38 (099) 917-19-25",
      "id": 10
    },
    {
      "name": "achhamana",
      "phone": "+38 (099) 917-19-25",
      "id": 11
    },
    {
      "name": "Nikita",
      "phone": "0736289394",
      "id": 12
    },
    {
      "name": "Nikita",
      "phone": "+38 (099) 917-19-25",
      "id": 13
    },
    {
      "name": "achhamana",
      "phone": "+38 (099) 917-19-25",
      "id": 14
    },
    {
      "name": "achhamana",
      "phone": "+38 (099) 917-19-25",
      "id": 15
    },
    {
      "name": "achhamana",
      "phone": "+38 (099) 917-19-25",
      "id": 16
    },
    {
      "name": "achhamana",
      "phone": "+38 (099) 917-19-25",
      "id": 17
    },
    {
      "name": "asd",
      "phone": "asd",
      "id": 18
    },
    {
      "name": "achhamana",
      "phone": "+38 (099) 917-19-25",
      "id": 19
    },
    {
      "name": "achhamana",
      "phone": "+38 (099) 917-19-25",
      "id": 20
    },
    {
      "name": "achhamana",
      "phone": "+38 (099) 917-19-25",
      "id": 21
    },
    {
      "name": "achhamana",
      "phone": "+38 (099) 917-19-25",
      "id": 22
    },
    {
      "name": "achhamana",
      "phone": "0736289394",
      "id": 23
    },
    {
      "name": "achhamana",
      "phone": "+38 (099) 917-19-25",
      "id": 24
    },
    {
      "name": "achhamana",
      "phone": "+38 (099) 917-19-25",
      "id": 25
    },
    {
      "name": "achhamana",
      "phone": "+38 (099) 917-19-25",
      "id": 26
    },
    {
      "name": "achhamana",
      "phone": "+38 (099) 917-19-25",
      "id": 27
    },
    {
      "name": "achhamana",
      "phone": "+38 (099) 917-19-25",
      "id": 28
    }
  ]
}